truenaspy/__init__.py
truenaspy/const.py
truenaspy/exceptions.py
truenaspy/helper.py
truenaspy/py.typed
truenaspy/subscription.py
truenaspy/websocket.py
truenaspy-1.0.3.dist-info/licenses/LICENSE
truenaspy-1.0.3.dist-info/METADATA
truenaspy-1.0.3.dist-info/WHEEL
truenaspy-1.0.3.dist-info/top_level.txt
truenaspy-1.0.3.dist-info/RECORD
