Metadata-Version: 2.4
Name: truenaspy
Version: 1.0.3
Summary: Provides asynchronous authentication and access to Truenas devices
Author-email: Cyr-ius <cyr-ius@ipocus.net>
License: GPL-3
Project-URL: Homepage, https://github.com/cyr-ius/truenaspy
Keywords: async,truenas,scale,core
Platform: any
Classifier: Programming Language :: Python
Classifier: Development Status :: 5 - Production/Stable
Classifier: License :: OSI Approved :: GNU General Public License v3 or later (GPLv3+)
Classifier: Programming Language :: Python :: 3
Classifier: Programming Language :: Python :: 3.12
Classifier: Framework :: AsyncIO
Classifier: Intended Audience :: Developers
Classifier: Intended Audience :: System Administrators
Classifier: Topic :: Home Automation
Requires-Python: >=3.12.0
License-File: LICENSE
Requires-Dist: aiohttp>=3.9.5
Requires-Dist: semantic_version>=2.10.0
Requires-Dist: mashumaro>=3.13
Dynamic: license-file
